baseport/__init__.py
baseport/cli.py
baseport/comments.py
baseport/util.py
baseport-0.2.0.dist-info/entry_points.txt
baseport-0.2.0.dist-info/LICENSE
baseport-0.2.0.dist-info/WHEEL
baseport-0.2.0.dist-info/METADATA
baseport-0.2.0.dist-info/RECORD
